test_123_testtt_123/__init__.py
test_123_testtt_123/core.py
test_123_testtt_123-0.1.0.dist-info/METADATA
test_123_testtt_123-0.1.0.dist-info/WHEEL
test_123_testtt_123-0.1.0.dist-info/top_level.txt
test_123_testtt_123-0.1.0.dist-info/RECORD
