Metadata-Version: 2.4
Name: test_123_testtt_123
Version: 0.1.0
Summary: Простой пакет для получения внешнего IP через 2ip.io
Author-email: Твое Имя <you@example.com>
License: MIT
Project-URL: Homepage, https://pypi.org/project/my-packet/
Requires-Python: >=3.8
Requires-Dist: requests
